{
  "footnote": "</br>\t\t",
  "content": "<span style=\"margin-left:15px;\"></span>Whoever commits mischief by killing, poisoning,\r\nmaiming or rendering useless any animal shall be punished with imprisonment of either description for a\r\nterm which may extend to five years, or with fine, or with both.</br><hr class=\"hr1\"/></br>",
  "_meta": {
    "act_slug": "05_20062",
    "act_id": "AC_CEN_5_23_00048_2023-45_1719292564123",
    "section_id": "90690",
    "orderno": 325,
    "url": "https://www.indiacode.nic.in/show-data?actid=AC_CEN_5_23_00048_2023-45_1719292564123&orderno=325"
  }
}